tests/__init__.py
tests/conftest.py
tests/test_notification.py
tests/test_validation.py
tests/test_verification.py
tests/test_verification_mixtures.py
tests/tks_utils.py
tks/__init__.py
tks/data/VERSION
tks/data/options.json
tks/provider/__init__.py
tks/provider/constants.py
tks/provider/tks.py
tks/provider/utils.py
tks/provider/models/__init__.py
tks/provider/models/guassian_mixtures_model.py
tks/provider/models/guassian_model.py
tesla_ce_provider_ks_tks-0.0.10.dist-info/LICENSE
tesla_ce_provider_ks_tks-0.0.10.dist-info/METADATA
tesla_ce_provider_ks_tks-0.0.10.dist-info/WHEEL
tesla_ce_provider_ks_tks-0.0.10.dist-info/top_level.txt
tesla_ce_provider_ks_tks-0.0.10.dist-info/RECORD
