Metadata-Version: 2.1
Name: tesla-ce-provider-ks-tks
Version: 0.0.10
Summary: TeSLA CE Keystroke Provider
Home-page: https://tesla-ce.github.io
Author: Roger Munoz
Author-email: rmunoz@uoc.edu
License: UNKNOWN
Project-URL: Documentation, https://tesla-ce.github.io/provider-ks-tks/
Project-URL: Source, https://github.com/tesla-ce/provider-ks-tks
Platform: UNKNOWN
Classifier: Programming Language :: Python :: 3
Classifier: License :: OSI Approved :: GNU Affero General Public License v3 or later (AGPLv3+)
Classifier: Operating System :: POSIX :: Linux
Requires-Python: >=3.8
License-File: LICENSE
Requires-Dist: joblib
Requires-Dist: numpy
Requires-Dist: scikit-learn
Requires-Dist: scipy
Requires-Dist: tesla-ce-provider (>=0.0.9)
